mvtcr/__init__.py
mvtcr/utils_preprocessing.py
mvtcr/utils_training.py
mvtcr/config_optuna/__init__.py
mvtcr/config_optuna/concat.py
mvtcr/config_optuna/concat_equal.py
mvtcr/config_optuna/mlp_count.py
mvtcr/config_optuna/moe.py
mvtcr/config_optuna/moe_equal.py
mvtcr/config_optuna/moe_supervised.py
mvtcr/config_optuna/poe.py
mvtcr/config_optuna/poe_equal.py
mvtcr/config_optuna/rna.py
mvtcr/config_optuna/tcr.py
mvtcr/dataloader/DataLoader.py
mvtcr/dataloader/Dataset.py
mvtcr/dataloader/__init__.py
mvtcr/evaluation/Clustering.py
mvtcr/evaluation/Imputation.py
mvtcr/evaluation/Metrics.py
mvtcr/evaluation/PertubationPrediction.py
mvtcr/evaluation/WrapperFunctions.py
mvtcr/evaluation/__init__.py
mvtcr/evaluation/kNN.py
mvtcr/models/__init__.py
mvtcr/models/model_selection.py
mvtcr/models/model_selection_count_prediction.py
mvtcr/models/pertubation_prediction.py
mvtcr/models/pertubation_prediction_orig.py
mvtcr/models/vae_base_model.py
mvtcr/models/architectures/__init__.py
mvtcr/models/architectures/bigru.py
mvtcr/models/architectures/cnn.py
mvtcr/models/architectures/mlp.py
mvtcr/models/architectures/mlp_count_prediction.py
mvtcr/models/architectures/mlp_scRNA.py
mvtcr/models/architectures/transformer.py
mvtcr/models/losses/__init__.py
mvtcr/models/losses/kld.py
mvtcr/models/losses/msle.py
mvtcr/models/losses/nb.py
mvtcr/models/mixture_modules/__init__.py
mvtcr/models/mixture_modules/moe.py
mvtcr/models/mixture_modules/poe.py
mvtcr/models/mixture_modules/rna_model.py
mvtcr/models/mixture_modules/separate_model.py
mvtcr/models/optimization/__init__.py
mvtcr/models/optimization/knn_prediction.py
mvtcr/models/optimization/modulation_prediction.py
mvtcr/models/optimization/pseudo_metric.py
mvtcr-0.2.1.2.dist-info/LICENSE
mvtcr-0.2.1.2.dist-info/METADATA
mvtcr-0.2.1.2.dist-info/WHEEL
mvtcr-0.2.1.2.dist-info/top_level.txt
mvtcr-0.2.1.2.dist-info/RECORD
