Metadata-Version: 2.1
Name: mvtcr
Version: 0.2.1.2
Summary: mvTCR: A multimodal generative model to learn a unified representation across TCR sequences and scRNAseq data for joint analysis of single-cell immune profiling data
Home-page: https://github.com/SchubertLab/mvTCR
Author: Felix Drost, Yang An, Lisa M Dratva, Rik GH Lindeboom, Muzlifah Haniffa, Sarah A Teichmann, Fabian Theis, Mohammad Lotfollahi, Benjamin Schubert
Maintainer: Felix Drost, Yang An, Irene Bonafonte Pardàs, Jan-Philipp Leusch
Classifier: Programming Language :: Python :: 3 :: Only
Classifier: Operating System :: Microsoft
Classifier: Operating System :: POSIX :: Linux
Classifier: Environment :: GPU :: NVIDIA CUDA
Classifier: Development Status :: 5 - Production/Stable
Classifier: Intended Audience :: Science/Research
Classifier: Intended Audience :: Healthcare Industry
Classifier: Natural Language :: English
Classifier: Topic :: Scientific/Engineering :: Artificial Intelligence
Classifier: Topic :: Scientific/Engineering :: Bio-Informatics
Classifier: Topic :: Scientific/Engineering :: Medical Science Apps.
License-File: LICENSE
Requires-Dist: anndata ==0.10.3
Requires-Dist: comet-ml ==3.35.5
Requires-Dist: leidenalg ==0.10.1
Requires-Dist: muon ==0.1.5
Requires-Dist: numba ==0.58.1
Requires-Dist: numpy ==1.26.1
Requires-Dist: optuna ==3.4.0
Requires-Dist: pandas ==2.1.1
Requires-Dist: scanpy ==1.9.6
Requires-Dist: scikit-learn ==1.3.2
Requires-Dist: scirpy ==0.13.1
Requires-Dist: scrublet ==0.2.3
Requires-Dist: tqdm ==4.66.1
Requires-Dist: umap-learn ==0.5.4
